cpplint_junit.py
cpplint_junit-2.0.1.data/scripts/cpplint_junit.py
cpplint_junit-2.0.1.dist-info/LICENSE.txt
cpplint_junit-2.0.1.dist-info/METADATA
cpplint_junit-2.0.1.dist-info/WHEEL
cpplint_junit-2.0.1.dist-info/entry_points.txt
cpplint_junit-2.0.1.dist-info/top_level.txt
cpplint_junit-2.0.1.dist-info/RECORD
